Workbook

Sheet vision_cleaned
A1: Effective Date | B1: Fund Name | C1: Option Name | D1: Asset Class Name | E1: Int/Ext | F1: Name/Kind of Investment Item | G1: Currency | H1: Stock ID | I1: Listed Country | J1: Units Held | K1: % Ownership | L1: Address | M1: Value (AUD) | N1: Weighting (%)
A2: 45657 | B2: Vision Super Fund | C2: Balanced growth | D2: Cash | E2: 1 | F2: JP Morgan Chase | G2: AUD | I2: =IF(ISBLANK(H2),"",INDEX(Sheet1!$F$2:$F$936,MATCH(H2,Sheet1!$C$2:$C$936,0))) | M2: -27694956 | N2: -0.0038
A3: 45657 | B3: Vision Super Fund | C3: Balanced growth | D3: Cash | E3: 1 | F3: AUSTRALIA & NEW ZEALAND BANKING GROUP LTD | G3: AUD | I3: =IF(ISBLANK(H3),"",INDEX(Sheet1!$F$2:$F$936,MATCH(H3,Sheet1!$C$2:$C$936,0))) | M3: 4079515.2 | N3: 0.0006
A4: 45657 | B4: Vision Super Fund | C4: Balanced growth | D4: Cash | E4: 1 | F4: CITI GROUP | G4: USD | I4: =IF(ISBLANK(H4),"",INDEX(Sheet1!$F$2:$F$936,MATCH(H4,Sheet1!$C$2:$C$936,0))) | M4: 446108.04 | N4: 0.0001
A5: 45657 | B5: Vision Super Fund | C5: Balanced growth | D5: Cash | E5: 1 | F5: Citibank | G5: AUD | I5: =IF(ISBLANK(H5),"",INDEX(Sheet1!$F$2:$F$936,MATCH(H5,Sheet1!$C$2:$C$936,0))) | M5: 110097.64 | N5: 0
A6: 45657 | B6: Vision Super Fund | C6: Balanced growth | D6: Cash | E6: 1 | F6: COMMONWEALTH BANK OF AUSTRALIA | G6: AUD | I6: =IF(ISBLANK(H6),"",INDEX(Sheet1!$F$2:$F$936,MATCH(H6,Sheet1!$C$2:$C$936,0))) | M6: 76540348 | N6: 0.0106
A7: 45657 | B7: Vision Super Fund | C7: Balanced growth | D7: Cash | E7: 1 | F7: CREDIT AGRICOLE CORP | G7: USD | I7: =IF(ISBLANK(H7),"",INDEX(Sheet1!$F$2:$F$936,MATCH(H7,Sheet1!$C$2:$C$936,0))) | M7: 22078.44 | N7: 0
A8: 45657 | B8: Vision Super Fund | C8: Balanced growth | D8: Cash | E8: 1 | F8: FINISTERRE EMD TRF | G8: AUD | I8: =IF(ISBLANK(H8),"",INDEX(Sheet1!$F$2:$F$936,MATCH(H8,Sheet1!$C$2:$C$936,0))) | M8: 46840410 | N8: 0.0065
A9: 45657 | B9: Vision Super Fund | C9: Balanced growth | D9: Cash | E9: 1 | F9: FINISTERRE EMD TRF | G9: BRL | I9: =IF(ISBLANK(H9),"",INDEX(Sheet1!$F$2:$F$936,MATCH(H9,Sheet1!$C$2:$C$936,0))) | M9: -2025471.7 | N9: -0.0003
A10: 45657 | B10: Vision Super Fund | C10: Balanced growth | D10: Cash | E10: 1 | F10: FINISTERRE EMD TRF | G10: CLP | I10: =IF(ISBLANK(H10),"",INDEX(Sheet1!$F$2:$F$936,MATCH(H10,Sheet1!$C$2:$C$936,0))) | M10: 522578.24 | N10: 0.0001
A11: 45657 | B11: Vision Super Fund | C11: Balanced growth | D11: Cash | E11: 1 | F11: FINISTERRE EMD TRF | G11: CNH | I11: =IF(ISBLANK(H11),"",INDEX(Sheet1!$F$2:$F$936,MATCH(H11,Sheet1!$C$2:$C$936,0))) | M11: -3676120.7 | N11: -0.0005
A12: 45657 | B12: Vision Super Fund | C12: Balanced growth | D12: Cash | E12: 1 | F12: FINISTERRE EMD TRF | G12: CZK | I12: =IF(ISBLANK(H12),"",INDEX(Sheet1!$F$2:$F$936,MATCH(H12,Sheet1!$C$2:$C$936,0))) | M12: -3606.6793 | N12: 0
A13: 45657 | B13: Vision Super Fund | C13: Balanced growth | D13: Cash | E13: 1 | F13: FINISTERRE EMD TRF | G13: EGP | I13: =IF(ISBLANK(H13),"",INDEX(Sheet1!$F$2:$F$936,MATCH(H13,Sheet1!$C$2:$C$936,0))) | M13: 703074.1 | N13: 0.0001
... A67: 45657 | B67: Vision Super Fund | C67: Balanced growth | D67: Cash | E67: 1 | F67: Vision Cash | G67: AUD | I67: =IF(ISBLANK(H67),"",INDEX(Sheet1!$F$2:$F$936,MATCH(H67,Sheet1!$C$2:$C$936,0))) | M67: -2993821.6 | N67: -0.0004
A68: 45657 | B68: Vision Super Fund | C68: Balanced growth | D68: Cash | E68: 1 | F68: Sub Total | I68: =IF(ISBLANK(H68),"",INDEX(Sheet1!$F$2:$F$936,MATCH(H68,Sheet1!$C$2:$C$936,0))) | M68: 3.0353834e+08 | N68: 0.0422
A69: 45657 | B69: Vision Super Fund | C69: Balanced growth | D69: Fixed Income Internal | E69: 0 | F69: AUSTRALIA & NEW ZEALAND BANKING GROUP LTD | I69: =IF(ISBLANK(H69),"",INDEX(Sheet1!$F$2:$F$936,MATCH(H69,Sheet1!$C$2:$C$936,0))) | M69: 11339775 | N69: 0.0016
A70: 45657 | B70: Vision Super Fund | C70: Balanced growth | D70: Fixed Income Internal | E70: 0 | F70: BANK OF QUEENSLAND LTD | I70: =IF(ISBLANK(H70),"",INDEX(Sheet1!$F$2:$F$936,MATCH(H70,Sheet1!$C$2:$C$936,0))) | M70: 41319805 | N70: 0.0057
A71: 45657 | B71: Vision Super Fund | C71: Balanced growth | D71: Fixed Income Internal | E71: 0 | F71: BENDIGO & ADELAIDE BANK LTD | I71: =IF(ISBLANK(H71),"",INDEX(Sheet1!$F$2:$F$936,MATCH(H71,Sheet1!$C$2:$C$936,0))) | M71: 58424440 | N71: 0.0081
A72: 45657 | B72: Vision Super Fund | C72: Balanced growth | D72: Fixed Income Internal | E72: 0 | F72: COMMONWEALTH BANK OF AUSTRALIA | I72: =IF(ISBLANK(H72),"",INDEX(Sheet1!$F$2:$F$936,MATCH(H72,Sheet1!$C$2:$C$936,0))) | M72: 34019584 | N72: 0.0047
A73: 45657 | B73: Vision Super Fund | C73: Balanced growth | D73: Fixed Income Internal | E73: 0 | F73: Norfina Limited | I73: =IF(ISBLANK(H73),"",INDEX(Sheet1!$F$2:$F$936,MATCH(H73,Sheet1!$C$2:$C$936,0))) | M73: 1.2692285e+08 | N73: 0.0176
A74: 45657 | B74: Vision Super Fund | C74: Balanced growth | D74: Fixed Income Internal | E74: 0 | F74: WESTPAC BANKING CORP | I74: =IF(ISBLANK(H74),"",INDEX(Sheet1!$F$2:$F$936,MATCH(H74,Sheet1!$C$2:$C$936,0))) | M74: 70747519 | N74: 0.0098
A75: 45657 | B75: Vision Super Fund | C75: Balanced growth | D75: Fixed Income Internal | E75: 0 | F75: Sub Total | I75: =IF(ISBLANK(H75),"",INDEX(Sheet1!$F$2:$F$936,MATCH(H75,Sheet1!$C$2:$C$936,0))) | M75: 3.4277397e+08 | N75: 0.0475
A76: 45657 | B76: Vision Super Fund | C76: Balanced growth | D76: Fixed Income External | E76: 1 | F76: Amundi Singapore Limited | I76: =IF(ISBLANK(H76),"",INDEX(Sheet1!$F$2:$F$936,MATCH(H76,Sheet1!$C$2:$C$936,0))) | M76: 8.7235174e+08 | N76: 0.1208
A77: 45657 | B77: Vision Super Fund | C77: Balanced growth | D77: Fixed Income External | E77: 1 | F77: Barings Global Advisers Limited | I77: =IF(ISBLANK(H77),"",INDEX(Sheet1!$F$2:$F$936,MATCH(H77,Sheet1!$C$2:$C$936,0))) | M77: 70867353 | N77: 0.0098
A78: 45657 | B78: Vision Super Fund | C78: Balanced growth | D78: Fixed Income External | E78: 1 | F78: Brandywine Global Investment Management, LLC | I78: =IF(ISBLANK(H78),"",INDEX(Sheet1!$F$2:$F$936,MATCH(H78,Sheet1!$C$2:$C$936,0))) | M78: 1.1700671e+08 | N78: 0.0162
A79: 45657 | B79: Vision Super Fund | C79: Balanced growth | D79: Fixed Income External | E79: 1 | F79: IFM Investors Pty Ltd | I79: =IF(ISBLANK(H79),"",INDEX(Sheet1!$F$2:$F$936,MATCH(H79,Sheet1!$C$2:$C$936,0))) | M79: 2.1002435e+08 | N79: 0.0291
... A82: 45657 | B82: Vision Super Fund | C82: Balanced growth | D82: Fixed Income External | E82: 1 | F82: Sub Total | I82: =IF(ISBLANK(H82),"",INDEX(Sheet1!$F$2:$F$936,MATCH(H82,Sheet1!$C$2:$C$936,0))) | M82: 1.4128488e+09 | N82: 0.1957
A83: 45657 | B83: Vision Super Fund | C83: Balanced growth | D83: Listed Equity | E83: 1 | F83: 29METALS LTD COMMON STOCK AUD | H83: BNNVRL0 | I83: =IF(ISBLANK(H83),"",INDEX(Sheet1!$F$2:$F$936,MATCH(H83,Sheet1!$C$2:$C$936,0))) -> Australia | J83: 2329363 | M83: 570693.85 | N83: 0.0001
A84: 45657 | B84: Vision Super Fund | C84: Balanced growth | D84: Listed Equity | E84: 1 | F84: 3I GROUP PLC COMMON STOCK GBP 73.8636 | H84: B1YW440 | I84: =IF(ISBLANK(H84),"",INDEX(Sheet1!$F$2:$F$936,MATCH(H84,Sheet1!$C$2:$C$936,0))) -> United Kingdom | J84: 34243 | M84: 2468616.6 | N84: 0.0003
A85: 45657 | B85: Vision Super Fund | C85: Balanced growth | D85: Listed Equity | E85: 1 | F85: A2 MILK CO LTD/THE COMMON STOCK NZD 0 | H85: 2F5232S | I85: =IF(ISBLANK(H85),"",INDEX(Sheet1!$F$2:$F$936,MATCH(H85,Sheet1!$C$2:$C$936,0))) -> NZD | J85: 287841 | M85: 1660843.3 | N85: 0.0002
A86: 45657 | B86: Vision Super Fund | C86: Balanced growth | D86: Listed Equity | E86: 1 | F86: ABB INDIA LTD COMMON STOCK INR 2 | H86: B1Y9QS9 | I86: =IF(ISBLANK(H86),"",INDEX(Sheet1!$F$2:$F$936,MATCH(H86,Sheet1!$C$2:$C$936,0))) -> INR | J86: 6043 | M86: 786440.09 | N86: 0.0001
A87: 45657 | B87: Vision Super Fund | C87: Balanced growth | D87: Listed Equity | E87: 1 | F87: ABB LTD COMMON STOCK CHF 0.12 | H87: 7108899 | I87: =IF(ISBLANK(H87),"",INDEX(Sheet1!$F$2:$F$936,MATCH(H87,Sheet1!$C$2:$C$936,0))) -> Switzerland | J87: 44228 | M87: 3867102.4 | N87: 0.0005
A88: 45657 | B88: Vision Super Fund | C88: Balanced growth | D88: Listed Equity | E88: 1 | F88: ABBOTT LABORATORIES COMMON STOCK USD 0 | H88: 2002305 | I88: =IF(ISBLANK(H88),"",INDEX(Sheet1!$F$2:$F$936,MATCH(H88,Sheet1!$C$2:$C$936,0))) -> United States | J88: 39262 | M88: 7174547.3 | N88: 0.001
A89: 45657 | B89: Vision Super Fund | C89: Balanced growth | D89: Listed Equity | E89: 1 | F89: ABBVIE INC COMMON STOCK USD 0.01 | H89: B92SR70 | I89: =IF(ISBLANK(H89),"",INDEX(Sheet1!$F$2:$F$936,MATCH(H89,Sheet1!$C$2:$C$936,0))) -> United States | J89: 35141 | M89: 10090817 | N89: 0.0014
A90: 45657 | B90: Vision Super Fund | C90: Balanced growth | D90: Listed Equity | E90: 1 | F90: ACCENT GROUP LTD COMMON STOCK AUD 0 | H90: BD20RS5 | I90: =IF(ISBLANK(H90),"",INDEX(Sheet1!$F$2:$F$936,MATCH(H90,Sheet1!$C$2:$C$936,0))) -> AUD | J90: 807271 | M90: 1889015.3 | N90: 0.0003
A91: 45657 | B91: Vision Super Fund | C91: Balanced growth | D91: Listed Equity | E91: 1 | F91: ACCENTURE PLC COMMON STOCK USD 0.0000225 | H91: B4BNMY3 | I91: =IF(ISBLANK(H91),"",INDEX(Sheet1!$F$2:$F$936,MATCH(H91,Sheet1!$C$2:$C$936,0))) -> United States | J91: 3300 | M91: 1876816.5 | N91: 0.0003
A92: 45657 | B92: Vision Super Fund | C92: Balanced growth | D92: Listed Equity | E92: 1 | F92: ACS ACTIVIDADES DE CONSTRUCCION Y SERVICIOS SA | H92: B01FLQ6 | I92: =IF(ISBLANK(H92),"",INDEX(Sheet1!$F$2:$F$936,MATCH(H92,Sheet1!$C$2:$C$936,0))) -> Spain | J92: 41234 | M92: 3340498.4 | N92: 0.0005
A93: 45657 | B93: Vision Super Fund | C93: Balanced growth | D93: Listed Equity | E93: 1 | F93: ADAIRS LTD COMMON STOCK AUD | H93: BYYT7Q5 | I93: =IF(ISBLANK(H93),"",INDEX(Sheet1!$F$2:$F$936,MATCH(H93,Sheet1!$C$2:$C$936,0))) -> AUD | J93: 435634 | M93: 1176211.7 | N93: 0.0002
A94: 45657 | B94: Vision Super Fund | C94: Balanced growth | D94: Listed Equity | E94: 1 | F94: ADOBE INC COMMON STOCK USD 0.0001 | H94: 2008154 | I94: =IF(ISBLANK(H94),"",INDEX(Sheet1!$F$2:$F$936,MATCH(H94,Sheet1!$C$2:$C$936,0))) -> United States | J94: 7598 | M94: 5456460.1 | N94: 0.0008
A95: 45657 | B95: Vision Super Fund | C95: Balanced growth | D95: Listed Equity | E95: 1 | F95: ADVANCED MICRO DEVICES INC COMMON STOCK USD 0.01 | H95: 2007849 | I95: =IF(ISBLANK(H95),"",INDEX(Sheet1!$F$2:$F$936,MATCH(H95,Sheet1!$C$2:$C$936,0))) -> United States | J95: 29622 | M95: 5778436.1 | N95: 0.0008
A96: 45657 | B96: Vision Super Fund | C96: Balanced growth | D96: Listed Equity | E96: 1 | F96: ADVANTEST CORP COMMON STOCK JPY | H96: 6870490 | I96: =IF(ISBLANK(H96),"",INDEX(Sheet1!$F$2:$F$936,MATCH(H96,Sheet1!$C$2:$C$936,0))) -> Japan | J96: 9800 | M96: 926330.27 | N96: 0.0001
A97: 45657 | B97: Vision Super Fund | C97: Balanced growth | D97: Listed Equity | E97: 1 | F97: ADYEN NV COMMON STOCK EUR 0.01 | H97: BZ1HM42 | I97: =IF(ISBLANK(H97),"",INDEX(Sheet1!$F$2:$F$936,MATCH(H97,Sheet1!$C$2:$C$936,0))) -> Netherlands | J97: 1570 | M97: 3754434.2 | N97: 0.0005
A98: 45657 | B98: Vision Super Fund | C98: Balanced growth | D98: Listed Equity | E98: 1 | F98: AERCAP HOLDINGS NV COMMON STOCK USD 0.01 | H98: B1HHKD3 | I98: =IF(ISBLANK(H98),"",INDEX(Sheet1!$F$2:$F$936,MATCH(H98,Sheet1!$C$2:$C$936,0))) -> Ireland | J98: 22623 | M98: 3497432 | N98: 0.0005
A99: 45657 | B99: Vision Super Fund | C99: Balanced growth | D99: Listed Equity | E99: 1 | F99: AFLAC INC COMMON STOCK USD 0.1 | H99: 2026361 | I99: =IF(ISBLANK(H99),"",INDEX(Sheet1!$F$2:$F$936,MATCH(H99,Sheet1!$C$2:$C$936,0))) -> United States | J99: 23920 | M99: 3997400.3 | N99: 0.0006
A100: 45657 | B100: Vision Super Fund | C100: Balanced growth | D100: Listed Equity | E100: 1 | F100: AGEAS SA/NV COMMON STOCK EUR 0 | H100: B86S2N0 | I100: =IF(ISBLANK(H100),"",INDEX(Sheet1!$F$2:$F$936,MATCH(H100,Sheet1!$C$2:$C$936,0))) -> Belgium | J100: 9497 | M100: 741742.65 | N100: 0.0001
A101: 45657 | B101: Vision Super Fund | C101: Balanced growth | D101: Listed Equity | E101: 1 | F101: AGILENT TECHNOLOGIES INC COMMON STOCK USD 0.01 | H101: 2520153 | I101: =IF(ISBLANK(H101),"",INDEX(Sheet1!$F$2:$F$936,MATCH(H101,Sheet1!$C$2:$C$936,0))) -> United States | J101: 9448 | M101: 2050695.7 | N101: 0.0003
A102: 45657 | B102: Vision Super Fund | C102: Balanced growth | D102: Listed Equity | E102: 1 | F102: AGNICO EAGLE MINES LTD COMMON STOCK CAD 0 | H102: 2009823 | I102: =IF(ISBLANK(H102),"",INDEX(Sheet1!$F$2:$F$936,MATCH(H102,Sheet1!$C$2:$C$936,0))) -> Canada | J102: 28427 | M102: 3587305.3 | N102: 0.0005
A103: 45657 | B103: Vision Super Fund | C103: Balanced growth | D103: Listed Equity | E103: 1 | F103: AIA GROUP LTD COMMON STOCK HKD 0 | H103: B4TX8S1 | I103: =IF(ISBLANK(H103),"",INDEX(Sheet1!$F$2:$F$936,MATCH(H103,Sheet1!$C$2:$C$936,0))) -> Hong Kong | J103: 395436 | M103: 4628946.1 | N103: 0.0006
A104: 45657 | B104: Vision Super Fund | C104: Balanced growth | D104: Listed Equity | E104: 1 | F104: AIB GROUP PLC COMMON STOCK EUR 0.625 | H104: BF0L353 | I104: =IF(ISBLANK(H104),"",INDEX(Sheet1!$F$2:$F$936,MATCH(H104,Sheet1!$C$2:$C$936,0))) -> Ireland | J104: 47839 | M104: 424841.77 | N104: 0.0001
A105: 45657 | B105: Vision Super Fund | C105: Balanced growth | D105: Listed Equity | E105: 1 | F105: AIR CANADA COMMON STOCK CAD 0 | H105: BSDHYK1 | I105: =IF(ISBLANK(H105),"",INDEX(Sheet1!$F$2:$F$936,MATCH(H105,Sheet1!$C$2:$C$936,0))) -> Canada | J105: 35225 | M105: 879778.35 | N105: 0.0001
A106: 45657 | B106: Vision Super Fund | C106: Balanced growth | D106: Listed Equity | E106: 1 | F106: AIRBUS SE COMMON STOCK EUR 1 | H106: 4012250 | I106: =IF(ISBLANK(H106),"",INDEX(Sheet1!$F$2:$F$936,MATCH(H106,Sheet1!$C$2:$C$936,0))) -> Netherlands | J106: 16060 | M106: 4153109.1 | N106: 0.0006
A107: 45657 | B107: Vision Super Fund | C107: Balanced growth | D107: Listed Equity | E107: 1 | F107: AKBANK TAS COMMON STOCK TRY 1 | H107: B03MN70 | I107: =IF(ISBLANK(H107),"",INDEX(Sheet1!$F$2:$F$936,MATCH(H107,Sheet1!$C$2:$C$936,0))) -> TRY | J107: 93852 | M107: 277996.5 | N107: 0
A108: 45657 | B108: Vision Super Fund | C108: Balanced growth | D108: Listed Equity | E108: 1 | F108: AL RAJHI BANK COMMON STOCK SAR 10 | H108: B12LZH9 | I108: =IF(ISBLANK(H108),"",INDEX(Sheet1!$F$2:$F$936,MATCH(H108,Sheet1!$C$2:$C$936,0))) -> SAR | J108: 8226 | M108: 334519.53 | N108: 0
A109: 45657 | B109: Vision Super Fund | C109: Balanced growth | D109: Listed Equity | E109: 1 | F109: ALDAR PROPERTIES PJSC COMMON STOCK AED 1 | H109: B0LX3Y2 | I109: =IF(ISBLANK(H109),"",INDEX(Sheet1!$F$2:$F$936,MATCH(H109,Sheet1!$C$2:$C$936,0))) -> UAE | J109: 130227 | M109: 439785.35 | N109: 0.0001
A110: 45657 | B110: Vision Super Fund | C110: Balanced growth | D110: Listed Equity | E110: 1 | F110: ALIBABA GROUP HOLDING LTD ADR USD 0.000025 | H110: BP41ZD1 | I110: =IF(ISBLANK(H110),"",INDEX(Sheet1!$F$2:$F$936,MATCH(H110,Sheet1!$C$2:$C$936,0))) -> China | J110: 13932 | M110: 1907465.2 | N110: 0.0003
A111: 45657 | B111: Vision Super Fund | C111: Balanced growth | D111: Listed Equity | E111: 1 | F111: ALIBABA GROUP HOLDING LTD COMMON STOCK HKD | H111: BK6YZP5 | I111: =IF(ISBLANK(H111),"",INDEX(Sheet1!$F$2:$F$936,MATCH(H111,Sheet1!$C$2:$C$936,0))) -> China | J111: 332187 | M111: 5691254.2 | N111: 0.0008
A112: 45657 | B112: Vision Super Fund | C112: Balanced growth | D112: Listed Equity | E112: 1 | F112: ALLEGION PLC COMMON STOCK USD 0.01 | H112: BFRT3W7 | I112: =IF(ISBLANK(H112),"",INDEX(Sheet1!$F$2:$F$936,MATCH(H112,Sheet1!$C$2:$C$936,0))) -> USD | J112: 948 | M112: 200247.81 | N112: 0
A113: 45657 | B113: Vision Super Fund | C113: Balanced growth | D113: Listed Equity | E113: 1 | F113: ALLIANZ SE COMMON STOCK EUR 0 | H113: 5231485 | I113: =IF(ISBLANK(H113),"",INDEX(Sheet1!$F$2:$F$936,MATCH(H113,Sheet1!$C$2:$C$936,0))) -> Germany | J113: 7111 | M113: 3515308.4 | N113: 0.0005
A114: 45657 | B114: Vision Super Fund | C114: Balanced growth | D114: Listed Equity | E114: 1 | F114: ALPHABET INC COMMON STOCK USD 0.001 | H114: BYVY8G0 | I114: =IF(ISBLANK(H114),"",INDEX(Sheet1!$F$2:$F$936,MATCH(H114,Sheet1!$C$2:$C$936,0))) -> United States | J114: 84657 | M114: 25885995 | N114: 0.0036
A115: 45657 | B115: Vision Super Fund | C115: Balanced growth | D115: Listed Equity | E115: 1 | F115: ALPHABET INC COMMON STOCK USD 0.001 | H115: BYY88Y7 | I115: =IF(ISBLANK(H115),"",INDEX(Sheet1!$F$2:$F$936,MATCH(H115,Sheet1!$C$2:$C$936,0))) -> United States | J115: 156746 | M115: 48209807 | N115: 0.0067
A116: 45657 | B116: Vision Super Fund | C116: Balanced growth | D116: Listed Equity | E116: 1 | F116: ALS LTD COMMON STOCK AUD 0 | H116: B86SZR5 | I116: =IF(ISBLANK(H116),"",INDEX(Sheet1!$F$2:$F$936,MATCH(H116,Sheet1!$C$2:$C$936,0))) -> Australia | J116: 184094 | M116: 2776144 | N116: 0.0004
A117: 45657 | B117: Vision Super Fund | C117: Balanced growth | D117: Listed Equity | E117: 1 | F117: AMADEUS IT GROUP SA COMMON STOCK EUR 0.01 | H117: B3MSM28 | I117: =IF(ISBLANK(H117),"",INDEX(Sheet1!$F$2:$F$936,MATCH(H117,Sheet1!$C$2:$C$936,0))) -> Spain | J117: 19838 | M117: 2222920.6 | N117: 0.0003
A118: 45657 | B118: Vision Super Fund | C118: Balanced growth | D118: Listed Equity | E118: 1 | F118: AMAZON.COM INC COMMON STOCK USD 0.01 | H118: 2000019 | I118: =IF(ISBLANK(H118),"",INDEX(Sheet1!$F$2:$F$936,MATCH(H118,Sheet1!$C$2:$C$936,0))) -> United States | J118: 192878 | M118: 68328759 | N118: 0.0095
A119: 45657 | B119: Vision Super Fund | C119: Balanced growth | D119: Listed Equity | E119: 1 | F119: AMCOR PLC CDI AUD 0 | H119: 3F0936S | I119: =IF(ISBLANK(H119),"",INDEX(Sheet1!$F$2:$F$936,MATCH(H119,Sheet1!$C$2:$C$936,0))) -> AUD | J119: 244464 | M119: 3654739.3 | N119: 0.0005
A120: 45657 | B120: Vision Super Fund | C120: Balanced growth | D120: Listed Equity | E120: 1 | F120: AMCOR PLC COMMON STOCK USD 0.01 | H120: BJ1F307 | I120: =IF(ISBLANK(H120),"",INDEX(Sheet1!$F$2:$F$936,MATCH(H120,Sheet1!$C$2:$C$936,0))) -> United Kingdom | J120: 174867 | M120: 2654841.5 | N120: 0.0004
A121: 45657 | B121: Vision Super Fund | C121: Balanced growth | D121: Listed Equity | E121: 1 | F121: AMERICAN EXPRESS CO COMMON STOCK USD 0.2 | H121: 2026082 | I121: =IF(ISBLANK(H121),"",INDEX(Sheet1!$F$2:$F$936,MATCH(H121,Sheet1!$C$2:$C$936,0))) -> United States | J121: 1594 | M121: 764228.71 | N121: 0.0001
A122: 45657 | B122: Vision Super Fund | C122: Balanced growth | D122: Listed Equity | E122: 1 | F122: AMERICAN INTERNATIONAL GROUP INC COMMON STOCK USD | H122: 2027342 | I122: =IF(ISBLANK(H122),"",INDEX(Sheet1!$F$2:$F$936,MATCH(H122,Sheet1!$C$2:$C$936,0))) -> United States | J122: 10458 | M122: 1229681.5 | N122: 0.0002
A123: 45657 | B123: Vision Super Fund | C123: Balanced growth | D123: Listed Equity | E123: 1 | F123: AMERICANA RESTAURANTS INTERNATIONAL PLC COMMON | H123: BP4X2F8 | I123: =IF(ISBLANK(H123),"",INDEX(Sheet1!$F$2:$F$936,MATCH(H123,Sheet1!$C$2:$C$936,0))) -> SA | J123: 585558 | M123: 571363.67 | N123: 0.0001
A124: 45657 | B124: Vision Super Fund | C124: Balanced growth | D124: Listed Equity | E124: 1 | F124: AMERIPRISE FINANCIAL INC COMMON STOCK USD 0.01 | H124: B0J7D57 | I124: =IF(ISBLANK(H124),"",INDEX(Sheet1!$F$2:$F$936,MATCH(H124,Sheet1!$C$2:$C$936,0))) -> United States | J124: 4707 | M124: 4049679.5 | N124: 0.0006
A125: 45657 | B125: Vision Super Fund | C125: Balanced growth | D125: Listed Equity | E125: 1 | F125: AMGEN INC COMMON STOCK USD 0.0001 | H125: 2023607 | I125: =IF(ISBLANK(H125),"",INDEX(Sheet1!$F$2:$F$936,MATCH(H125,Sheet1!$C$2:$C$936,0))) -> United States | J125: 9972 | M125: 4197577.3 | N125: 0.0006
A126: 45657 | B126: Vision Super Fund | C126: Balanced growth | D126: Listed Equity | E126: 1 | F126: AMOTIV LTD COMMON STOCK AUD 0 | H126: BQH8HH4 | I126: =IF(ISBLANK(H126),"",INDEX(Sheet1!$F$2:$F$936,MATCH(H126,Sheet1!$C$2:$C$936,0))) -> AUD | J126: 759854 | M126: 8054454 | N126: 0.0011
A127: 45657 | B127: Vision Super Fund | C127: Balanced growth | D127: Listed Equity | E127: 1 | F127: AMP LTD COMMON STOCK AUD 0 | H127: 6709958 | I127: =IF(ISBLANK(H127),"",INDEX(Sheet1!$F$2:$F$936,MATCH(H127,Sheet1!$C$2:$C$936,0))) -> Australia | J127: 1153079 | M127: 1827631 | N127: 0.0003
A128: 45657 | B128: Vision Super Fund | C128: Balanced growth | D128: Listed Equity | E128: 1 | F128: AMPHENOL CORP COMMON STOCK USD 0.001 | H128: 2145084 | I128: =IF(ISBLANK(H128),"",INDEX(Sheet1!$F$2:$F$936,MATCH(H128,Sheet1!$C$2:$C$936,0))) -> United States | J128: 3106 | M128: 348550.37 | N128: 0
A129: 45657 | B129: Vision Super Fund | C129: Balanced growth | D129: Listed Equity | E129: 1 | F129: AMPOL LTD COMMON STOCK AUD 0 | H129: BM91201 | I129: =IF(ISBLANK(H129),"",INDEX(Sheet1!$F$2:$F$936,MATCH(H129,Sheet1!$C$2:$C$936,0))) -> Australia | J129: 712685 | M129: 20062076 | N129: 0.0028
A130: 45657 | B130: Vision Super Fund | C130: Balanced growth | D130: Listed Equity | E130: 1 | F130: ANALOG DEVICES INC COMMON STOCK USD 0.167 | H130: 2032067 | I130: =IF(ISBLANK(H130),"",INDEX(Sheet1!$F$2:$F$936,MATCH(H130,Sheet1!$C$2:$C$936,0))) -> United States | J130: 11172 | M130: 3833509.1 | N130: 0.0005
A131: 45657 | B131: Vision Super Fund | C131: Balanced growth | D131: Listed Equity | E131: 1 | F131: ANSELL LTD COMMON STOCK AUD 0 | H131: 3F0097S | I131: =IF(ISBLANK(H131),"",INDEX(Sheet1!$F$2:$F$936,MATCH(H131,Sheet1!$C$2:$C$936,0))) -> AUD | J131: 57048 | M131: 1928805.3 | N131: 0.0003
A132: 45657 | B132: Vision Super Fund | C132: Balanced growth | D132: Listed Equity | E132: 1 | F132: ANTA SPORTS PRODUCTS LTD COMMON STOCK HKD 0.1 | H132: B1YVKN8 | I132: =IF(ISBLANK(H132),"",INDEX(Sheet1!$F$2:$F$936,MATCH(H132,Sheet1!$C$2:$C$936,0))) -> HKD | J132: 215229 | M132: 3483837.1 | N132: 0.0005
A133: 45657 | B133: Vision Super Fund | C133: Balanced growth | D133: Listed Equity | E133: 1 | F133: ANZ GROUP HOLDINGS LTD COMMON STOCK AUD 0 | H133: 6065586 | I133: =IF(ISBLANK(H133),"",INDEX(Sheet1!$F$2:$F$936,MATCH(H133,Sheet1!$C$2:$C$936,0))) -> Australia | J133: 1446192 | M133: 41274319 | N133: 0.0057
A134: 45657 | B134: Vision Super Fund | C134: Balanced growth | D134: Listed Equity | E134: 1 | F134: APOLLO GLOBAL MANAGEMENT INC COMMON STOCK USD | H134: BN44JF6 | I134: =IF(ISBLANK(H134),"",INDEX(Sheet1!$F$2:$F$936,MATCH(H134,Sheet1!$C$2:$C$936,0))) -> United States | J134: 2987 | M134: 797214.43 | N134: 0.0001
A135: 45657 | B135: Vision Super Fund | C135: Balanced growth | D135: Listed Equity | E135: 1 | F135: APOLLO HOSPITALS ENTERPRISE LTD COMMON STOCK INR 5 | H135: 6273583 | I135: =IF(ISBLANK(H135),"",INDEX(Sheet1!$F$2:$F$936,MATCH(H135,Sheet1!$C$2:$C$936,0))) -> INR | J135: 23551 | M135: 3241526.4 | N135: 0.0004
A136: 45657 | B136: Vision Super Fund | C136: Balanced growth | D136: Listed Equity | E136: 1 | F136: APPEN LTD COMMON STOCK AUD 0 | H136: BTPJH25 | I136: =IF(ISBLANK(H136),"",INDEX(Sheet1!$F$2:$F$936,MATCH(H136,Sheet1!$C$2:$C$936,0))) -> AUD | J136: 388407 | M136: 1025393.6 | N136: 0.0001
A137: 45657 | B137: Vision Super Fund | C137: Balanced growth | D137: Listed Equity | E137: 1 | F137: APPLE INC COMMON STOCK USD 0.00001 | H137: 2046251 | I137: =IF(ISBLANK(H137),"",INDEX(Sheet1!$F$2:$F$936,MATCH(H137,Sheet1!$C$2:$C$936,0))) -> United States | J137: 243452 | M137: 98454126 | N137: 0.0136
A138: 45657 | B138: Vision Super Fund | C138: Balanced growth | D138: Listed Equity | E138: 1 | F138: APPLIED MATERIALS INC COMMON STOCK USD 0.01 | H138: 2046552 | I138: =IF(ISBLANK(H138),"",INDEX(Sheet1!$F$2:$F$936,MATCH(H138,Sheet1!$C$2:$C$936,0))) -> United States | J138: 19037 | M138: 5000377.3 | N138: 0.0007
A139: 45657 | B139: Vision Super Fund | C139: Balanced growth | D139: Listed Equity | E139: 1 | F139: APPLOVIN CORP COMMON STOCK USD 0.00003 | H139: BMV3LG4 | I139: =IF(ISBLANK(H139),"",INDEX(Sheet1!$F$2:$F$936,MATCH(H139,Sheet1!$C$2:$C$936,0))) -> United States | J139: 6065 | M139: 3172837 | N139: 0.0004
A140: 45657 | B140: Vision Super Fund | C140: Balanced growth | D140: Listed Equity | E140: 1 | F140: ARAB NATIONAL BANK COMMON STOCK SAR 10 | H140: B12LZK2 | I140: =IF(ISBLANK(H140),"",INDEX(Sheet1!$F$2:$F$936,MATCH(H140,Sheet1!$C$2:$C$936,0))) -> SAR | J140: 135752 | M140: 1230079.8 | N140: 0.0002
A141: 45657 | B141: Vision Super Fund | C141: Balanced growth | D141: Listed Equity | E141: 1 | F141: ARB CORP LTD COMMON STOCK AUD 0 | H141: BWV03W5 | I141: =IF(ISBLANK(H141),"",INDEX(Sheet1!$F$2:$F$936,MATCH(H141,Sheet1!$C$2:$C$936,0))) -> Australia | J141: 40189 | M141: 1632080.4 | N141: 0.0002
A142: 45657 | B142: Vision Super Fund | C142: Balanced growth | D142: Listed Equity | E142: 1 | F142: ARCA CONTINENTAL SAB DE CV COMMON STOCK MXN 0 | H142: 2823885 | I142: =IF(ISBLANK(H142),"",INDEX(Sheet1!$F$2:$F$936,MATCH(H142,Sheet1!$C$2:$C$936,0))) -> MXN | J142: 33169 | M142: 443717.55 | N142: 0.0001
A143: 45657 | B143: Vision Super Fund | C143: Balanced growth | D143: Listed Equity | E143: 1 | F143: ARISTOCRAT LEISURE LTD | H143: 6253983 | I143: =IF(ISBLANK(H143),"",INDEX(Sheet1!$F$2:$F$936,MATCH(H143,Sheet1!$C$2:$C$936,0))) -> Australia | J143: 657540 | M143: 44949412 | N143: 0.0062
A144: 45657 | B144: Vision Super Fund | C144: Balanced growth | D144: Listed Equity | E144: 1 | F144: ASAHI KASEI CORP COMMON STOCK JPY | H144: 6054603 | I144: =IF(ISBLANK(H144),"",INDEX(Sheet1!$F$2:$F$936,MATCH(H144,Sheet1!$C$2:$C$936,0))) -> Japan | J144: 235775 | M144: 2641106.9 | N144: 0.0004
A145: 45657 | B145: Vision Super Fund | C145: Balanced growth | D145: Listed Equity | E145: 1 | F145: ASIAN PAINTS LTD COMMON STOCK INR 1 | H145: BCRWL65 | I145: =IF(ISBLANK(H145),"",INDEX(Sheet1!$F$2:$F$936,MATCH(H145,Sheet1!$C$2:$C$936,0))) -> INR | J145: 15601 | M145: 671923.2 | N145: 0.0001
A146: 45657 | B146: Vision Super Fund | C146: Balanced growth | D146: Listed Equity | E146: 1 | F146: ASICS CORP COMMON STOCK JPY | H146: 6057378 | I146: =IF(ISBLANK(H146),"",INDEX(Sheet1!$F$2:$F$936,MATCH(H146,Sheet1!$C$2:$C$936,0))) -> Japan | J146: 38615 | M146: 1234188.6 | N146: 0.0002
A147: 45657 | B147: Vision Super Fund | C147: Balanced growth | D147: Listed Equity | E147: 1 | F147: ASML HOLDING NV COMMON STOCK EUR 0.09 | H147: B929F46 | I147: =IF(ISBLANK(H147),"",INDEX(Sheet1!$F$2:$F$936,MATCH(H147,Sheet1!$C$2:$C$936,0))) -> Netherlands | J147: 6834 | M147: 7749752.6 | N147: 0.0011
A148: 45657 | B148: Vision Super Fund | C148: Balanced growth | D148: Listed Equity | E148: 1 | F148: ASML HOLDING NV NY REG SHRS USD 0.09 | H148: B908F01 | I148: =IF(ISBLANK(H148),"",INDEX(Sheet1!$F$2:$F$936,MATCH(H148,Sheet1!$C$2:$C$936,0))) -> Netherlands | J148: 2004 | M148: 2241328.8 | N148: 0.0003
A149: 45657 | B149: Vision Super Fund | C149: Balanced growth | D149: Listed Equity | E149: 1 | F149: ASTELLAS PHARMA INC COMMON STOCK JPY | H149: 6985383 | I149: =IF(ISBLANK(H149),"",INDEX(Sheet1!$F$2:$F$936,MATCH(H149,Sheet1!$C$2:$C$936,0))) -> Japan | J149: 113804 | M149: 1794096.5 | N149: 0.0002
A150: 45657 | B150: Vision Super Fund | C150: Balanced growth | D150: Listed Equity | E150: 1 | F150: ASTRAZENECA PLC ADR USD | H150: 2989044 | I150: =IF(ISBLANK(H150),"",INDEX(Sheet1!$F$2:$F$936,MATCH(H150,Sheet1!$C$2:$C$936,0))) -> United Kingdom | J150: 41257 | M150: 4363935.4 | N150: 0.0006
A151: 45657 | B151: Vision Super Fund | C151: Balanced growth | D151: Listed Equity | E151: 1 | F151: ASTRAZENECA PLC COMMON STOCK GBP 0.25 | H151: 989529 | I151: =IF(ISBLANK(H151),"",INDEX(Sheet1!$F$2:$F$936,MATCH(H151,Sheet1!$C$2:$C$936,0))) -> United Kingdom | J151: 13945 | M151: 2951692.2 | N151: 0.0004
A152: 45657 | B152: Vision Super Fund | C152: Balanced growth | D152: Listed Equity | E152: 1 | F152: ASUSTEK COMPUTER INC COMMON STOCK TWD 10 | H152: 6051046 | I152: =IF(ISBLANK(H152),"",INDEX(Sheet1!$F$2:$F$936,MATCH(H152,Sheet1!$C$2:$C$936,0))) -> Taiwan | J152: 41998 | M152: 1274529.3 | N152: 0.0002
A153: 45657 | B153: Vision Super Fund | C153: Balanced growth | D153: Listed Equity | E153: 1 | F153: ASX LTD COMMON STOCK AUD 0 | H153: 6129222 | I153: =IF(ISBLANK(H153),"",INDEX(Sheet1!$F$2:$F$936,MATCH(H153,Sheet1!$C$2:$C$936,0))) -> Australia | J153: 79996 | M153: 5206144.3 | N153: 0.0007
A154: 45657 | B154: Vision Super Fund | C154: Balanced growth | D154: Listed Equity | E154: 1 | F154: AT&T INC COMMON STOCK USD 1 | H154: 2831811 | I154: =IF(ISBLANK(H154),"",INDEX(Sheet1!$F$2:$F$936,MATCH(H154,Sheet1!$C$2:$C$936,0))) -> United States | J154: 158592 | M154: 5834958.5 | N154: 0.0008
A155: 45657 | B155: Vision Super Fund | C155: Balanced growth | D155: Listed Equity | E155: 1 | F155: ATLASSIAN CORP COMMON STOCK USD 0.00001 | H155: BQ1PC76 | I155: =IF(ISBLANK(H155),"",INDEX(Sheet1!$F$2:$F$936,MATCH(H155,Sheet1!$C$2:$C$936,0))) -> United States | J155: 13217 | M155: 5192245 | N155: 0.0007
...

Sheet Sheet1
B1: Name | C1: Stock Id | D1: cross check with Ausie Super | E1: Manual | F1: Combine
B2: 29METALS LTD COMMON STOCK AUD | C2: BNNVRL0 | D2: Australia | F2: =_xlfn.IFNA(D2,E2) -> Australia | I2: {=SUM(INT(ISNA(D2:D936)))} -> 326 | J2: =I2/COUNTA(C2:C936) -> 0.3486631
B3: 3I GROUP PLC COMMON STOCK GBP 73.8636 | C3: B1YW440 | D3: United Kingdom | F3: =_xlfn.IFNA(D3,E3) -> United Kingdom
B4: A2 MILK CO LTD/THE COMMON STOCK NZD 0 | C4: 2F5232S | D4: #N/A | E4: NZD | F4: =_xlfn.IFNA(D4,E4) -> NZD
B5: ABB INDIA LTD COMMON STOCK INR 2 | C5: B1Y9QS9 | D5: #N/A | E5: INR | F5: =_xlfn.IFNA(D5,E5) -> INR
B6: ABB LTD COMMON STOCK CHF 0.12 | C6: 7108899 | D6: Switzerland | F6: =_xlfn.IFNA(D6,E6) -> Switzerland
B7: ABBOTT LABORATORIES COMMON STOCK USD 0 | C7: 2002305 | D7: United States | F7: =_xlfn.IFNA(D7,E7) -> United States
B8: ABBVIE INC COMMON STOCK USD 0.01 | C8: B92SR70 | D8: United States | F8: =_xlfn.IFNA(D8,E8) -> United States
B9: ACCENT GROUP LTD COMMON STOCK AUD 0 | C9: BD20RS5 | D9: #N/A | E9: AUD | F9: =_xlfn.IFNA(D9,E9) -> AUD
B10: ACCENTURE PLC COMMON STOCK USD 0.0000225 | C10: B4BNMY3 | D10: United States | F10: =_xlfn.IFNA(D10,E10) -> United States
B11: ACS ACTIVIDADES DE CONSTRUCCION Y SERVICIOS SA | C11: B01FLQ6 | D11: Spain | F11: =_xlfn.IFNA(D11,E11) -> Spain
B12: ADAIRS LTD COMMON STOCK AUD | C12: BYYT7Q5 | D12: #N/A | E12: AUD | F12: =_xlfn.IFNA(D12,E12) -> AUD
B13: ADOBE INC COMMON STOCK USD 0.0001 | C13: 2008154 | D13: United States | F13: =_xlfn.IFNA(D13,E13) -> United States
B14: ADVANCED MICRO DEVICES INC COMMON STOCK USD 0.01 | C14: 2007849 | D14: United States | F14: =_xlfn.IFNA(D14,E14) -> United States
B15: ADVANTEST CORP COMMON STOCK JPY | C15: 6870490 | D15: Japan | F15: =_xlfn.IFNA(D15,E15) -> Japan
B16: ADYEN NV COMMON STOCK EUR 0.01 | C16: BZ1HM42 | D16: Netherlands | F16: =_xlfn.IFNA(D16,E16) -> Netherlands
B17: AERCAP HOLDINGS NV COMMON STOCK USD 0.01 | C17: B1HHKD3 | D17: Ireland | F17: =_xlfn.IFNA(D17,E17) -> Ireland
B18: AFLAC INC COMMON STOCK USD 0.1 | C18: 2026361 | D18: United States | F18: =_xlfn.IFNA(D18,E18) -> United States
B19: AGEAS SA/NV COMMON STOCK EUR 0 | C19: B86S2N0 | D19: Belgium | F19: =_xlfn.IFNA(D19,E19) -> Belgium
B20: AGILENT TECHNOLOGIES INC COMMON STOCK USD 0.01 | C20: 2520153 | D20: United States | F20: =_xlfn.IFNA(D20,E20) -> United States
B21: AGNICO EAGLE MINES LTD COMMON STOCK CAD 0 | C21: 2009823 | D21: Canada | F21: =_xlfn.IFNA(D21,E21) -> Canada
B22: AIA GROUP LTD COMMON STOCK HKD 0 | C22: B4TX8S1 | D22: Hong Kong | F22: =_xlfn.IFNA(D22,E22) -> Hong Kong
B23: AIB GROUP PLC COMMON STOCK EUR 0.625 | C23: BF0L353 | D23: Ireland | F23: =_xlfn.IFNA(D23,E23) -> Ireland
B24: AIR CANADA COMMON STOCK CAD 0 | C24: BSDHYK1 | D24: Canada | F24: =_xlfn.IFNA(D24,E24) -> Canada
B25: AIRBUS SE COMMON STOCK EUR 1 | C25: 4012250 | D25: Netherlands | F25: =_xlfn.IFNA(D25,E25) -> Netherlands
B26: AKBANK TAS COMMON STOCK TRY 1 | C26: B03MN70 | D26: #N/A | E26: TRY | F26: =_xlfn.IFNA(D26,E26) -> TRY
B27: AL RAJHI BANK COMMON STOCK SAR 10 | C27: B12LZH9 | D27: #N/A | E27: SAR | F27: =_xlfn.IFNA(D27,E27) -> SAR
B28: ALDAR PROPERTIES PJSC COMMON STOCK AED 1 | C28: B0LX3Y2 | D28: UAE | F28: =_xlfn.IFNA(D28,E28) -> UAE
B29: ALIBABA GROUP HOLDING LTD ADR USD 0.000025 | C29: BP41ZD1 | D29: China | F29: =_xlfn.IFNA(D29,E29) -> China
B30: ALIBABA GROUP HOLDING LTD COMMON STOCK HKD | C30: BK6YZP5 | D30: China | F30: =_xlfn.IFNA(D30,E30) -> China
B31: ALLEGION PLC COMMON STOCK USD 0.01 | C31: BFRT3W7 | D31: #N/A | E31: USD | F31: =_xlfn.IFNA(D31,E31) -> USD
B32: ALLIANZ SE COMMON STOCK EUR 0 | C32: 5231485 | D32: Germany | F32: =_xlfn.IFNA(D32,E32) -> Germany
B33: ALPHABET INC COMMON STOCK USD 0.001 | C33: BYVY8G0 | D33: United States | F33: =_xlfn.IFNA(D33,E33) -> United States
B34: ALPHABET INC COMMON STOCK USD 0.001 | C34: BYY88Y7 | D34: United States | F34: =_xlfn.IFNA(D34,E34) -> United States
B35: ALS LTD COMMON STOCK AUD 0 | C35: B86SZR5 | D35: Australia | F35: =_xlfn.IFNA(D35,E35) -> Australia
B36: AMADEUS IT GROUP SA COMMON STOCK EUR 0.01 | C36: B3MSM28 | D36: Spain | F36: =_xlfn.IFNA(D36,E36) -> Spain
B37: AMAZON.COM INC COMMON STOCK USD 0.01 | C37: 2000019 | D37: United States | F37: =_xlfn.IFNA(D37,E37) -> United States
B38: AMCOR PLC CDI AUD 0 | C38: 3F0936S | D38: #N/A | E38: AUD | F38: =_xlfn.IFNA(D38,E38) -> AUD
B39: AMCOR PLC COMMON STOCK USD 0.01 | C39: BJ1F307 | D39: United Kingdom | F39: =_xlfn.IFNA(D39,E39) -> United Kingdom
B40: AMERICAN EXPRESS CO COMMON STOCK USD 0.2 | C40: 2026082 | D40: United States | F40: =_xlfn.IFNA(D40,E40) -> United States
B41: AMERICAN INTERNATIONAL GROUP INC COMMON STOCK USD | C41: 2027342 | D41: United States | F41: =_xlfn.IFNA(D41,E41) -> United States
B42: AMERICANA RESTAURANTS INTERNATIONAL PLC COMMON | C42: BP4X2F8 | D42: #N/A | E42: SA | F42: =_xlfn.IFNA(D42,E42) -> SA
B43: AMERIPRISE FINANCIAL INC COMMON STOCK USD 0.01 | C43: B0J7D57 | D43: United States | F43: =_xlfn.IFNA(D43,E43) -> United States
B44: AMGEN INC COMMON STOCK USD 0.0001 | C44: 2023607 | D44: United States | F44: =_xlfn.IFNA(D44,E44) -> United States
B45: AMOTIV LTD COMMON STOCK AUD 0 | C45: BQH8HH4 | D45: #N/A | E45: AUD | F45: =_xlfn.IFNA(D45,E45) -> AUD
B46: AMP LTD COMMON STOCK AUD 0 | C46: 6709958 | D46: Australia | F46: =_xlfn.IFNA(D46,E46) -> Australia
B47: AMPHENOL CORP COMMON STOCK USD 0.001 | C47: 2145084 | D47: United States | F47: =_xlfn.IFNA(D47,E47) -> United States
B48: AMPOL LTD COMMON STOCK AUD 0 | C48: BM91201 | D48: Australia | F48: =_xlfn.IFNA(D48,E48) -> Australia
B49: ANALOG DEVICES INC COMMON STOCK USD 0.167 | C49: 2032067 | D49: United States | F49: =_xlfn.IFNA(D49,E49) -> United States
B50: ANSELL LTD COMMON STOCK AUD 0 | C50: 3F0097S | D50: #N/A | E50: AUD | F50: =_xlfn.IFNA(D50,E50) -> AUD
B51: ANTA SPORTS PRODUCTS LTD COMMON STOCK HKD 0.1 | C51: B1YVKN8 | D51: #N/A | E51: HKD | F51: =_xlfn.IFNA(D51,E51) -> HKD
B52: ANZ GROUP HOLDINGS LTD COMMON STOCK AUD 0 | C52: 6065586 | D52: Australia | F52: =_xlfn.IFNA(D52,E52) -> Australia
B53: APOLLO GLOBAL MANAGEMENT INC COMMON STOCK USD | C53: BN44JF6 | D53: United States | F53: =_xlfn.IFNA(D53,E53) -> United States
B54: APOLLO HOSPITALS ENTERPRISE LTD COMMON STOCK INR 5 | C54: 6273583 | D54: #N/A | E54: INR | F54: =_xlfn.IFNA(D54,E54) -> INR
B55: APPEN LTD COMMON STOCK AUD 0 | C55: BTPJH25 | D55: #N/A | E55: AUD | F55: =_xlfn.IFNA(D55,E55) -> AUD
B56: APPLE INC COMMON STOCK USD 0.00001 | C56: 2046251 | D56: United States | F56: =_xlfn.IFNA(D56,E56) -> United States
B57: APPLIED MATERIALS INC COMMON STOCK USD 0.01 | C57: 2046552 | D57: United States | F57: =_xlfn.IFNA(D57,E57) -> United States
B58: APPLOVIN CORP COMMON STOCK USD 0.00003 | C58: BMV3LG4 | D58: United States | F58: =_xlfn.IFNA(D58,E58) -> United States
B59: ARAB NATIONAL BANK COMMON STOCK SAR 10 | C59: B12LZK2 | D59: #N/A | E59: SAR | F59: =_xlfn.IFNA(D59,E59) -> SAR
B60: ARB CORP LTD COMMON STOCK AUD 0 | C60: BWV03W5 | D60: Australia | F60: =_xlfn.IFNA(D60,E60) -> Australia
B61: ARCA CONTINENTAL SAB DE CV COMMON STOCK MXN 0 | C61: 2823885 | D61: #N/A | E61: MXN | F61: =_xlfn.IFNA(D61,E61) -> MXN
B62: ARISTOCRAT LEISURE LTD | C62: 6253983 | D62: Australia | F62: =_xlfn.IFNA(D62,E62) -> Australia
B63: ASAHI KASEI CORP COMMON STOCK JPY | C63: 6054603 | D63: Japan | F63: =_xlfn.IFNA(D63,E63) -> Japan
B64: ASIAN PAINTS LTD COMMON STOCK INR 1 | C64: BCRWL65 | D64: #N/A | E64: INR | F64: =_xlfn.IFNA(D64,E64) -> INR
B65: ASICS CORP COMMON STOCK JPY | C65: 6057378 | D65: Japan | F65: =_xlfn.IFNA(D65,E65) -> Japan
B66: ASML HOLDING NV COMMON STOCK EUR 0.09 | C66: B929F46 | D66: Netherlands | F66: =_xlfn.IFNA(D66,E66) -> Netherlands
B67: ASML HOLDING NV NY REG SHRS USD 0.09 | C67: B908F01 | D67: Netherlands | F67: =_xlfn.IFNA(D67,E67) -> Netherlands
B68: ASTELLAS PHARMA INC COMMON STOCK JPY | C68: 6985383 | D68: Japan | F68: =_xlfn.IFNA(D68,E68) -> Japan
B69: ASTRAZENECA PLC ADR USD | C69: 2989044 | D69: United Kingdom | F69: =_xlfn.IFNA(D69,E69) -> United Kingdom
B70: ASTRAZENECA PLC COMMON STOCK GBP 0.25 | C70: 989529 | D70: United Kingdom | F70: =_xlfn.IFNA(D70,E70) -> United Kingdom
B71: ASUSTEK COMPUTER INC COMMON STOCK TWD 10 | C71: 6051046 | D71: Taiwan | F71: =_xlfn.IFNA(D71,E71) -> Taiwan
B72: ASX LTD COMMON STOCK AUD 0 | C72: 6129222 | D72: Australia | F72: =_xlfn.IFNA(D72,E72) -> Australia
B73: AT&T INC COMMON STOCK USD 1 | C73: 2831811 | D73: United States | F73: =_xlfn.IFNA(D73,E73) -> United States
B74: ATLASSIAN CORP COMMON STOCK USD 0.00001 | C74: BQ1PC76 | D74: United States | F74: =_xlfn.IFNA(D74,E74) -> United States
B75: AUB GROUP LTD COMMON STOCK AUD 0 | C75: B0MBNC3 | D75: #N/A | E75: AUD | F75: =_xlfn.IFNA(D75,E75) -> AUD
B76: AUCKLAND INTERNATIONAL AIRPORT LTD COMMON STOCK | C76: 3F0911S | D76: #N/A | E76: NZ | F76: =_xlfn.IFNA(D76,E76) -> NZ
B77: AURELIA METALS LTD COMMON STOCK AUD 0 | C77: BN790Y4 | D77: #N/A | E77: AUD | F77: =_xlfn.IFNA(D77,E77) -> AUD
B78: AURIZON HOLDINGS LTD COMMON STOCK AUD | C78: B87CVM3 | D78: Australia | F78: =_xlfn.IFNA(D78,E78) -> Australia
B79: AUSSIE BROADBAND LTD COMMON STOCK AUD | C79: BM8HZC3 | D79: #N/A | E79: AUD | F79: =_xlfn.IFNA(D79,E79) -> AUD
B80: AUSTAL LTD COMMON STOCK AUD 0 | C80: 6137162 | D80: #N/A | E80: AUD | F80: =_xlfn.IFNA(D80,E80) -> AUD
B81: AUSTIN ENGINEERING LTD COMMON STOCK AUD 0 | C81: 6710615 | D81: #N/A | E81: AUD | F81: =_xlfn.IFNA(D81,E81) -> AUD
B82: AUSTRALIAN CLINICAL LABS LTD COMMON STOCK AUD | C82: BMWLLJ0 | D82: #N/A | E82: AUD | F82: =_xlfn.IFNA(D82,E82) -> AUD
B83: AUSTRALIAN FINANCE GROUP LTD COMMON STOCK AUD | C83: BY4K6K5 | D83: #N/A | E83: AUD | F83: =_xlfn.IFNA(D83,E83) -> AUD
B84: AUSWIDE BANK LTD COMMON STOCK AUD 0 | C84: BWCHB54 | D84: #N/A | E84: AUD | F84: =_xlfn.IFNA(D84,E84) -> AUD
B85: AUTOMATIC DATA PROCESSING INC COMMON STOCK USD 0.1 | C85: 2065308 | D85: United States | F85: =_xlfn.IFNA(D85,E85) -> United States
B86: AUTOSPORTS GROUP LTD COMMON STOCK AUD | C86: BZBHBJ0 | D86: #N/A | E86: AUD | F86: =_xlfn.IFNA(D86,E86) -> AUD
B87: AVENUE SUPERMARTS LTD COMMON STOCK INR 10 | C87: BYW1G33 | D87: #N/A | E87: INR | F87: =_xlfn.IFNA(D87,E87) -> INR
B88: AVERY DENNISON CORP COMMON STOCK USD 1 | C88: 2066408 | D88: United States | F88: =_xlfn.IFNA(D88,E88) -> United States
B89: AVIVA PLC COMMON STOCK GBP 32.89474 | C89: BPQY8M8 | D89: United Kingdom | F89: =_xlfn.IFNA(D89,E89) -> United Kingdom
B90: AXA SA COMMON STOCK EUR 2.29 | C90: 7088429 | D90: France | F90: =_xlfn.IFNA(D90,E90) -> France
B91: BABY BUNTING GROUP LTD COMMON STOCK AUD | C91: BYRJS58 | D91: Australia | F91: =_xlfn.IFNA(D91,E91) -> Australia
B92: BAE SYSTEMS PLC | C92: 263494 | D92: United Kingdom | F92: =_xlfn.IFNA(D92,E92) -> United Kingdom
B93: BAJAJ AUTO LTD COMMON STOCK INR 10 | C93: B2QKXW0 | D93: #N/A | E93: INR | F93: =_xlfn.IFNA(D93,E93) -> INR
B94: BAJAJ FINANCE LTD COMMON STOCK INR 2 | C94: BD2N0P2 | D94: #N/A | E94: INR | F94: =_xlfn.IFNA(D94,E94) -> INR
B95: BAKER HUGHES CO COMMON STOCK USD 0.0001 | C95: BDHLTQ5 | D95: United States | F95: =_xlfn.IFNA(D95,E95) -> United States
B96: BANCO BILBAO VIZCAYA ARGENTARIA SA COMMON STOCK | C96: 5501906 | D96: Spain | F96: =_xlfn.IFNA(D96,E96) -> Spain
B97: BANCOLOMBIA SA PREFERENCE COP 500 | C97: BJ62LW1 | D97: #N/A | E97: COP | F97: =_xlfn.IFNA(D97,E97) -> COP
B98: BANDAI NAMCO HOLDINGS INC COMMON STOCK JPY | C98: B0JDQD4 | D98: Japan | F98: =_xlfn.IFNA(D98,E98) -> Japan
B99: BANK CENTRAL ASIA TBK PT COMMON STOCK IDR 12.5 | C99: B01C1P6 | D99: Indonesia | F99: =_xlfn.IFNA(D99,E99) -> Indonesia
B100: BANK LEUMI LE-ISRAEL BM COMMON STOCK ILS 0.1 | C100: 6076425 | D100: Israel | F100: =_xlfn.IFNA(D100,E100) -> Israel
...
